{
  "topic": "CARMI",
  "slug": "carmi",
  "sources": [
    "NAV"
  ],
  "see_also": [],
  "aspects": [
    {
      "label": "1.",
      "references": [
        "Genesis 46:9",
        "Exodus 6:14"
      ],
      "source": "NAV"
    },
    {
      "label": "2.",
      "references": [
        "1 Chronicles 4:1"
      ],
      "source": "NAV"
    },
    {
      "label": ".",
      "references": [
        "1 Chronicles 2:9"
      ],
      "source": "NAV"
    },
    {
      "label": ".And",
      "references": [
        "1 Chronicles 2:18"
      ],
      "source": "NAV"
    },
    {
      "label": "3. Father of Achan",
      "references": [
        "Joshua 7:1,18",
        "1 Chronicles 2:7"
      ],
      "source": "NAV"
    }
  ],
  "biblical_references": [
    {
      "book": "Genesis",
      "chapter": 46,
      "verses": [
        9
      ],
      "verse_count": 1,
      "testament": "OT",
      "raw": "Genesis 46:9"
    },
    {
      "book": "Exodus",
      "chapter": 6,
      "verses": [
        14
      ],
      "verse_count": 1,
      "testament": "OT",
      "raw": "Exodus 6:14"
    },
    {
      "book": "1 Chronicles",
      "chapter": 4,
      "verses": [
        1
      ],
      "verse_count": 1,
      "testament": "OT",
      "raw": "1 Chronicles 4:1"
    },
    {
      "book": "1 Chronicles",
      "chapter": 2,
      "verses": [
        9
      ],
      "verse_count": 1,
      "testament": "OT",
      "raw": "1 Chronicles 2:9"
    },
    {
      "book": "1 Chronicles",
      "chapter": 2,
      "verses": [
        18
      ],
      "verse_count": 1,
      "testament": "OT",
      "raw": "1 Chronicles 2:18"
    },
    {
      "book": "Joshua",
      "chapter": 7,
      "verses": [
        1,
        18
      ],
      "verse_count": 2,
      "testament": "OT",
      "raw": "Joshua 7:1,18"
    },
    {
      "book": "1 Chronicles",
      "chapter": 2,
      "verses": [
        7
      ],
      "verse_count": 1,
      "testament": "OT",
      "raw": "1 Chronicles 2:7"
    }
  ],
  "books_mentioned": [
    "1 Chronicles",
    "Exodus",
    "Genesis",
    "Joshua"
  ],
  "stats": {
    "total_aspects": 5,
    "total_refs": 7,
    "ot_refs": 7,
    "nt_refs": 0,
    "books_count": 4,
    "top_books": [
      "1 Chronicles",
      "Genesis",
      "Exodus",
      "Joshua"
    ]
  }
}