{
  "topic": "ROME",
  "slug": "rome",
  "sources": [
    "NAV"
  ],
  "see_also": [
    "PAUL"
  ],
  "aspects": [
    {
      "label": "(The",
      "references": [],
      "source": "NAV"
    },
    {
      "label": "Jews exc",
      "references": [
        "Acts 18:2"
      ],
      "source": "NAV"
    },
    {
      "label": "Paul’ s visit to",
      "references": [],
      "source": "NAV"
    },
    {
      "label": ".SeePAUL",
      "references": [],
      "source": "NAV"
    },
    {
      "label": "Visited by Onesiphorus",
      "references": [
        "2 Timothy 1:16,17"
      ],
      "source": "NAV"
    },
    {
      "label": "Paul",
      "references": [
        "Romans 1:15"
      ],
      "source": "NAV"
    },
    {
      "label": "Abominations in",
      "references": [
        "Romans 1:18-32"
      ],
      "source": "NAV"
    },
    {
      "label": "Christians in",
      "references": [
        "Romans 16:5-17",
        "Philippians 1:12-18",
        "Philippians 4:22",
        "2 Timothy 4:21"
      ],
      "source": "NAV"
    },
    {
      "label": "Paul’ s letter to the Christians in",
      "references": [
        "Romans 1:7"
      ],
      "source": "NAV"
    },
    {
      "label": "Paul testifies the gospel of Christ to the",
      "references": [
        "Romans 1:16"
      ],
      "source": "NAV"
    },
    {
      "label": "The con",
      "references": [
        "Romans 1:18"
      ],
      "source": "NAV"
    },
    {
      "label": "The con",
      "references": [],
      "source": "NAV"
    },
    {
      "label": "God’ s",
      "references": [
        "Romans 2:6"
      ],
      "source": "NAV"
    },
    {
      "label": "Justifi",
      "references": [
        "Romans 3:24"
      ],
      "source": "NAV"
    },
    {
      "label": "The faith of Abraha",
      "references": [],
      "source": "NAV"
    },
    {
      "label": "The fruits of faith",
      "references": [
        "Romans 5:7"
      ],
      "source": "NAV"
    },
    {
      "label": "The works of the flesh and the SpiritRo 8",
      "references": [],
      "source": "NAV"
    },
    {
      "label": "God’ s supreme power over everyoneRo 9;11",
      "references": [],
      "source": "NAV"
    },
    {
      "label": "The righteousness the law and of faithRo 10",
      "references": [],
      "source": "NAV"
    },
    {
      "label": "Exhorted humility, love, and good worksRo 12",
      "references": [],
      "source": "NAV"
    },
    {
      "label": "To obey magistratesRo 13",
      "references": [],
      "source": "NAV"
    },
    {
      "label": "For mutual forbearance",
      "references": [
        "Romans 14:15"
      ],
      "source": "NAV"
    },
    {
      "label": "Requested to greet various brethrenRo 16",
      "references": [],
      "source": "NAV"
    }
  ],
  "biblical_references": [
    {
      "book": "Acts",
      "chapter": 18,
      "verses": [
        2
      ],
      "verse_count": 1,
      "testament": "NT",
      "raw": "Acts 18:2"
    },
    {
      "book": "2 Timothy",
      "chapter": 1,
      "verses": [
        16,
        17
      ],
      "verse_count": 2,
      "testament": "NT",
      "raw": "2 Timothy 1:16,17"
    },
    {
      "book": "Romans",
      "chapter": 1,
      "verses": [
        15
      ],
      "verse_count": 1,
      "testament": "NT",
      "raw": "Romans 1:15"
    },
    {
      "book": "Romans",
      "chapter": 1,
      "verses": [
        18,
        19,
        20,
        21,
        22,
        23,
        24,
        25,
        26,
        27,
        28,
        29,
        30,
        31,
        32
      ],
      "verse_count": 15,
      "testament": "NT",
      "raw": "Romans 1:18-32"
    },
    {
      "book": "Romans",
      "chapter": 16,
      "verses": [
        5,
        6,
        7,
        8,
        9,
        10,
        11,
        12,
        13,
        14,
        15,
        16,
        17
      ],
      "verse_count": 13,
      "testament": "NT",
      "raw": "Romans 16:5-17"
    },
    {
      "book": "Philippians",
      "chapter": 1,
      "verses": [
        12,
        13,
        14,
        15,
        16,
        17,
        18
      ],
      "verse_count": 7,
      "testament": "NT",
      "raw": "Philippians 1:12-18"
    },
    {
      "book": "Philippians",
      "chapter": 4,
      "verses": [
        22
      ],
      "verse_count": 1,
      "testament": "NT",
      "raw": "Philippians 4:22"
    },
    {
      "book": "2 Timothy",
      "chapter": 4,
      "verses": [
        21
      ],
      "verse_count": 1,
      "testament": "NT",
      "raw": "2 Timothy 4:21"
    },
    {
      "book": "Romans",
      "chapter": 1,
      "verses": [
        7
      ],
      "verse_count": 1,
      "testament": "NT",
      "raw": "Romans 1:7"
    },
    {
      "book": "Romans",
      "chapter": 1,
      "verses": [
        16
      ],
      "verse_count": 1,
      "testament": "NT",
      "raw": "Romans 1:16"
    },
    {
      "book": "Romans",
      "chapter": 1,
      "verses": [
        18
      ],
      "verse_count": 1,
      "testament": "NT",
      "raw": "Romans 1:18"
    },
    {
      "book": "Romans",
      "chapter": 2,
      "verses": [
        6
      ],
      "verse_count": 1,
      "testament": "NT",
      "raw": "Romans 2:6"
    },
    {
      "book": "Romans",
      "chapter": 3,
      "verses": [
        24
      ],
      "verse_count": 1,
      "testament": "NT",
      "raw": "Romans 3:24"
    },
    {
      "book": "Romans",
      "chapter": 5,
      "verses": [
        7
      ],
      "verse_count": 1,
      "testament": "NT",
      "raw": "Romans 5:7"
    },
    {
      "book": "Romans",
      "chapter": 14,
      "verses": [
        15
      ],
      "verse_count": 1,
      "testament": "NT",
      "raw": "Romans 14:15"
    }
  ],
  "books_mentioned": [
    "2 Timothy",
    "Acts",
    "Philippians",
    "Romans"
  ],
  "stats": {
    "total_aspects": 23,
    "total_refs": 15,
    "ot_refs": 0,
    "nt_refs": 15,
    "books_count": 4,
    "top_books": [
      "Romans",
      "2 Timothy",
      "Philippians",
      "Acts"
    ]
  }
}