{
  "topic": "PATRIARCH",
  "slug": "patriarch",
  "sources": [
    "NAV"
  ],
  "see_also": [],
  "aspects": [
    {
      "label": "Head of a family",
      "references": [
        "Acts 7:9"
      ],
      "source": "NAV"
    }
  ],
  "biblical_references": [
    {
      "book": "Acts",
      "chapter": 7,
      "verses": [
        9
      ],
      "verse_count": 1,
      "testament": "NT",
      "raw": "Acts 7:9"
    }
  ],
  "books_mentioned": [
    "Acts"
  ],
  "stats": {
    "total_aspects": 1,
    "total_refs": 1,
    "ot_refs": 0,
    "nt_refs": 1,
    "books_count": 1,
    "top_books": [
      "Acts"
    ]
  }
}