{
  "topic": "SALLAI",
  "slug": "sallai",
  "sources": [
    "NAV"
  ],
  "see_also": [],
  "aspects": [
    {
      "label": "1. A Benjamite living in",
      "references": [
        "Nehemiah 11:8"
      ],
      "source": "NAV"
    },
    {
      "label": "2. A priest who returned to",
      "references": [
        "Nehemiah 12:20"
      ],
      "source": "NAV"
    },
    {
      "label": ".",
      "references": [
        "Nehemiah 12:7"
      ],
      "source": "NAV"
    }
  ],
  "biblical_references": [
    {
      "book": "Nehemiah",
      "chapter": 11,
      "verses": [
        8
      ],
      "verse_count": 1,
      "testament": "OT",
      "raw": "Nehemiah 11:8"
    },
    {
      "book": "Nehemiah",
      "chapter": 12,
      "verses": [
        20
      ],
      "verse_count": 1,
      "testament": "OT",
      "raw": "Nehemiah 12:20"
    },
    {
      "book": "Nehemiah",
      "chapter": 12,
      "verses": [
        7
      ],
      "verse_count": 1,
      "testament": "OT",
      "raw": "Nehemiah 12:7"
    }
  ],
  "books_mentioned": [
    "Nehemiah"
  ],
  "stats": {
    "total_aspects": 3,
    "total_refs": 3,
    "ot_refs": 3,
    "nt_refs": 0,
    "books_count": 1,
    "top_books": [
      "Nehemiah"
    ]
  }
}