{
  "topic": "SIGN",
  "slug": "sign",
  "sources": [
    "NAV"
  ],
  "see_also": [
    "MIRACLES "
  ],
  "aspects": [
    {
      "label": "A miracle to confirm faith",
      "references": [
        "Matthew 12:38",
        "Matthew 16:4",
        "Matthew 24:3,30",
        "Mark 8:11,12",
        "Mark 13:4",
        "John 2:11",
        "John 3:2",
        "John 4:48"
      ],
      "source": "NAV"
    },
    {
      "label": "Asked for by, and given to",
      "references": [],
      "source": "NAV"
    },
    {
      "label": ".Abraham",
      "references": [
        "Genesis 15:8-17"
      ],
      "source": "NAV"
    },
    {
      "label": ".Moses",
      "references": [
        "Exodus 4:1-9"
      ],
      "source": "NAV"
    },
    {
      "label": ".Gi",
      "references": [
        "Judges 6:17,36-40"
      ],
      "source": "NAV"
    },
    {
      "label": ".Hezekiah",
      "references": [
        "2 Kings 20:8"
      ],
      "source": "NAV"
    },
    {
      "label": ".Zacharias",
      "references": [
        "Luke 1:18"
      ],
      "source": "NAV"
    },
    {
      "label": "Given to",
      "references": [
        "1 Kings 13:3-5"
      ],
      "source": "NAV"
    },
    {
      "label": "A token of coming events",
      "references": [
        "Matthew 16:3,4",
        "Matthew 24:3"
      ],
      "source": "NAV"
    },
    {
      "label": "SeeMIRACLES",
      "references": [],
      "source": "NAV"
    }
  ],
  "biblical_references": [
    {
      "book": "Matthew",
      "chapter": 12,
      "verses": [
        38
      ],
      "verse_count": 1,
      "testament": "NT",
      "raw": "Matthew 12:38"
    },
    {
      "book": "Matthew",
      "chapter": 16,
      "verses": [
        4
      ],
      "verse_count": 1,
      "testament": "NT",
      "raw": "Matthew 16:4"
    },
    {
      "book": "Matthew",
      "chapter": 24,
      "verses": [
        3,
        30
      ],
      "verse_count": 2,
      "testament": "NT",
      "raw": "Matthew 24:3,30"
    },
    {
      "book": "Mark",
      "chapter": 8,
      "verses": [
        11,
        12
      ],
      "verse_count": 2,
      "testament": "NT",
      "raw": "Mark 8:11,12"
    },
    {
      "book": "Mark",
      "chapter": 13,
      "verses": [
        4
      ],
      "verse_count": 1,
      "testament": "NT",
      "raw": "Mark 13:4"
    },
    {
      "book": "John",
      "chapter": 2,
      "verses": [
        11
      ],
      "verse_count": 1,
      "testament": "NT",
      "raw": "John 2:11"
    },
    {
      "book": "John",
      "chapter": 3,
      "verses": [
        2
      ],
      "verse_count": 1,
      "testament": "NT",
      "raw": "John 3:2"
    },
    {
      "book": "John",
      "chapter": 4,
      "verses": [
        48
      ],
      "verse_count": 1,
      "testament": "NT",
      "raw": "John 4:48"
    },
    {
      "book": "Genesis",
      "chapter": 15,
      "verses": [
        8,
        9,
        10,
        11,
        12,
        13,
        14,
        15,
        16,
        17
      ],
      "verse_count": 10,
      "testament": "OT",
      "raw": "Genesis 15:8-17"
    },
    {
      "book": "Exodus",
      "chapter": 4,
      "verses": [
        1,
        2,
        3,
        4,
        5,
        6,
        7,
        8,
        9
      ],
      "verse_count": 9,
      "testament": "OT",
      "raw": "Exodus 4:1-9"
    },
    {
      "book": "Judges",
      "chapter": 6,
      "verses": [
        17,
        36,
        37,
        38,
        39,
        40
      ],
      "verse_count": 6,
      "testament": "OT",
      "raw": "Judges 6:17,36-40"
    },
    {
      "book": "2 Kings",
      "chapter": 20,
      "verses": [
        8
      ],
      "verse_count": 1,
      "testament": "OT",
      "raw": "2 Kings 20:8"
    },
    {
      "book": "Luke",
      "chapter": 1,
      "verses": [
        18
      ],
      "verse_count": 1,
      "testament": "NT",
      "raw": "Luke 1:18"
    },
    {
      "book": "1 Kings",
      "chapter": 13,
      "verses": [
        3,
        4,
        5
      ],
      "verse_count": 3,
      "testament": "OT",
      "raw": "1 Kings 13:3-5"
    },
    {
      "book": "Matthew",
      "chapter": 16,
      "verses": [
        3,
        4
      ],
      "verse_count": 2,
      "testament": "NT",
      "raw": "Matthew 16:3,4"
    },
    {
      "book": "Matthew",
      "chapter": 24,
      "verses": [
        3
      ],
      "verse_count": 1,
      "testament": "NT",
      "raw": "Matthew 24:3"
    }
  ],
  "books_mentioned": [
    "1 Kings",
    "2 Kings",
    "Exodus",
    "Genesis",
    "John",
    "Judges",
    "Luke",
    "Mark",
    "Matthew"
  ],
  "stats": {
    "total_aspects": 10,
    "total_refs": 16,
    "ot_refs": 5,
    "nt_refs": 11,
    "books_count": 9,
    "top_books": [
      "Matthew",
      "John",
      "Mark",
      "Genesis",
      "Exodus",
      "Judges",
      "2 Kings",
      "Luke",
      "1 Kings"
    ]
  }
}