{
  "topic": "EAR-RING",
  "slug": "ear_ring",
  "sources": [
    "NAV"
  ],
  "see_also": [],
  "aspects": [
    {
      "label": "Of gold",
      "references": [
        "Proverbs 25:12"
      ],
      "source": "NAV"
    },
    {
      "label": "Offering of",
      "references": [],
      "source": "NAV"
    },
    {
      "label": ".For the gol",
      "references": [
        "Exodus 32:2,3"
      ],
      "source": "NAV"
    },
    {
      "label": ".For the tabernacle",
      "references": [
        "Exodus 35:22"
      ],
      "source": "NAV"
    },
    {
      "label": "Worn for idolatrous purposes",
      "references": [
        "Genesis 35:4",
        "Isaiah 3:20"
      ],
      "source": "NAV"
    }
  ],
  "biblical_references": [
    {
      "book": "Proverbs",
      "chapter": 25,
      "verses": [
        12
      ],
      "verse_count": 1,
      "testament": "OT",
      "raw": "Proverbs 25:12"
    },
    {
      "book": "Exodus",
      "chapter": 32,
      "verses": [
        2,
        3
      ],
      "verse_count": 2,
      "testament": "OT",
      "raw": "Exodus 32:2,3"
    },
    {
      "book": "Exodus",
      "chapter": 35,
      "verses": [
        22
      ],
      "verse_count": 1,
      "testament": "OT",
      "raw": "Exodus 35:22"
    },
    {
      "book": "Genesis",
      "chapter": 35,
      "verses": [
        4
      ],
      "verse_count": 1,
      "testament": "OT",
      "raw": "Genesis 35:4"
    },
    {
      "book": "Isaiah",
      "chapter": 3,
      "verses": [
        20
      ],
      "verse_count": 1,
      "testament": "OT",
      "raw": "Isaiah 3:20"
    }
  ],
  "books_mentioned": [
    "Exodus",
    "Genesis",
    "Isaiah",
    "Proverbs"
  ],
  "stats": {
    "total_aspects": 5,
    "total_refs": 5,
    "ot_refs": 5,
    "nt_refs": 0,
    "books_count": 4,
    "top_books": [
      "Exodus",
      "Proverbs",
      "Genesis",
      "Isaiah"
    ]
  }
}