{
  "topic": "DAMASCUS",
  "slug": "damascus",
  "sources": [
    "NAV"
  ],
  "see_also": [
    "SYRIA"
  ],
  "aspects": [
    {
      "label": "An ancient city",
      "references": [
        "Genesis 14:15",
        "Genesis 15:2"
      ],
      "source": "NAV"
    },
    {
      "label": "General references",
      "references": [
        "1 Kings 20:34",
        "Isaiah 7:8",
        "Jeremiah 49:23-29",
        "Ezekiel 47:16,17"
      ],
      "source": "NAV"
    },
    {
      "label": "Laid un",
      "references": [
        "2 Samuel 8:5,6"
      ],
      "source": "NAV"
    },
    {
      "label": "Besieged by Rezon",
      "references": [
        "1 Kings 11:23,24"
      ],
      "source": "NAV"
    },
    {
      "label": "Recovered by",
      "references": [
        "2 Kings 14:28"
      ],
      "source": "NAV"
    },
    {
      "label": "Taken by king of Assyria",
      "references": [
        "2 Kings 16:9"
      ],
      "source": "NAV"
    },
    {
      "label": "Walled",
      "references": [
        "Jeremiah 49:27",
        "2 Corinthians 11:33"
      ],
      "source": "NAV"
    },
    {
      "label": "Garri",
      "references": [
        "2 Corinthians 11:32"
      ],
      "source": "NAV"
    },
    {
      "label": "General references",
      "references": [
        "Amos 3:12"
      ],
      "source": "NAV"
    },
    {
      "label": "Paul’s experiences inAc 9;",
      "references": [],
      "source": "NAV"
    },
    {
      "label": "11:32;",
      "references": [
        "Galatians 1:17"
      ],
      "source": "NAV"
    },
    {
      "label": "Prophecies concerning",
      "references": [
        "Isaiah 8:4",
        "Isaiah 17:1,2",
        "Jeremiah 49:23-29",
        "Amos 1:3,5",
        "Ecclesiastes 9:1"
      ],
      "source": "NAV"
    },
    {
      "label": "Wil",
      "references": [
        "1 Kings 19:15"
      ],
      "source": "NAV"
    },
    {
      "label": "SeeSYRIA",
      "references": [],
      "source": "NAV"
    }
  ],
  "biblical_references": [
    {
      "book": "Genesis",
      "chapter": 14,
      "verses": [
        15
      ],
      "verse_count": 1,
      "testament": "OT",
      "raw": "Genesis 14:15"
    },
    {
      "book": "Genesis",
      "chapter": 15,
      "verses": [
        2
      ],
      "verse_count": 1,
      "testament": "OT",
      "raw": "Genesis 15:2"
    },
    {
      "book": "1 Kings",
      "chapter": 20,
      "verses": [
        34
      ],
      "verse_count": 1,
      "testament": "OT",
      "raw": "1 Kings 20:34"
    },
    {
      "book": "Isaiah",
      "chapter": 7,
      "verses": [
        8
      ],
      "verse_count": 1,
      "testament": "OT",
      "raw": "Isaiah 7:8"
    },
    {
      "book": "Jeremiah",
      "chapter": 49,
      "verses": [
        23,
        24,
        25,
        26,
        27,
        28,
        29
      ],
      "verse_count": 7,
      "testament": "OT",
      "raw": "Jeremiah 49:23-29"
    },
    {
      "book": "Ezekiel",
      "chapter": 47,
      "verses": [
        16,
        17
      ],
      "verse_count": 2,
      "testament": "OT",
      "raw": "Ezekiel 47:16,17"
    },
    {
      "book": "2 Samuel",
      "chapter": 8,
      "verses": [
        5,
        6
      ],
      "verse_count": 2,
      "testament": "OT",
      "raw": "2 Samuel 8:5,6"
    },
    {
      "book": "1 Kings",
      "chapter": 11,
      "verses": [
        23,
        24
      ],
      "verse_count": 2,
      "testament": "OT",
      "raw": "1 Kings 11:23,24"
    },
    {
      "book": "2 Kings",
      "chapter": 14,
      "verses": [
        28
      ],
      "verse_count": 1,
      "testament": "OT",
      "raw": "2 Kings 14:28"
    },
    {
      "book": "2 Kings",
      "chapter": 16,
      "verses": [
        9
      ],
      "verse_count": 1,
      "testament": "OT",
      "raw": "2 Kings 16:9"
    },
    {
      "book": "Jeremiah",
      "chapter": 49,
      "verses": [
        27
      ],
      "verse_count": 1,
      "testament": "OT",
      "raw": "Jeremiah 49:27"
    },
    {
      "book": "2 Corinthians",
      "chapter": 11,
      "verses": [
        33
      ],
      "verse_count": 1,
      "testament": "NT",
      "raw": "2 Corinthians 11:33"
    },
    {
      "book": "2 Corinthians",
      "chapter": 11,
      "verses": [
        32
      ],
      "verse_count": 1,
      "testament": "NT",
      "raw": "2 Corinthians 11:32"
    },
    {
      "book": "Amos",
      "chapter": 3,
      "verses": [
        12
      ],
      "verse_count": 1,
      "testament": "OT",
      "raw": "Amos 3:12"
    },
    {
      "book": "Amos",
      "chapter": 22,
      "verses": [
        5,
        6,
        7,
        8,
        9,
        10,
        11,
        12,
        13,
        14,
        15,
        16
      ],
      "verse_count": 12,
      "testament": "OT",
      "raw": "Amos 22:5-16"
    },
    {
      "book": "Amos",
      "chapter": 26,
      "verses": [
        12,
        13,
        14,
        15,
        16,
        17,
        18,
        19,
        20
      ],
      "verse_count": 9,
      "testament": "OT",
      "raw": "Amos 26:12-20"
    },
    {
      "book": "Amos",
      "chapter": 11,
      "verses": [
        32
      ],
      "verse_count": 1,
      "testament": "OT",
      "raw": "Amos 11:32"
    },
    {
      "book": "Galatians",
      "chapter": 1,
      "verses": [
        17
      ],
      "verse_count": 1,
      "testament": "NT",
      "raw": "Galatians 1:17"
    },
    {
      "book": "Isaiah",
      "chapter": 8,
      "verses": [
        4
      ],
      "verse_count": 1,
      "testament": "OT",
      "raw": "Isaiah 8:4"
    },
    {
      "book": "Isaiah",
      "chapter": 17,
      "verses": [
        1,
        2
      ],
      "verse_count": 2,
      "testament": "OT",
      "raw": "Isaiah 17:1,2"
    },
    {
      "book": "Amos",
      "chapter": 1,
      "verses": [
        3,
        5
      ],
      "verse_count": 2,
      "testament": "OT",
      "raw": "Amos 1:3,5"
    },
    {
      "book": "Ecclesiastes",
      "chapter": 9,
      "verses": [
        1
      ],
      "verse_count": 1,
      "testament": "OT",
      "raw": "Ecclesiastes 9:1"
    },
    {
      "book": "1 Kings",
      "chapter": 19,
      "verses": [
        15
      ],
      "verse_count": 1,
      "testament": "OT",
      "raw": "1 Kings 19:15"
    }
  ],
  "books_mentioned": [
    "1 Kings",
    "2 Corinthians",
    "2 Kings",
    "2 Samuel",
    "Amos",
    "Ecclesiastes",
    "Ezekiel",
    "Galatians",
    "Genesis",
    "Isaiah",
    "Jeremiah"
  ],
  "stats": {
    "total_aspects": 14,
    "total_refs": 23,
    "ot_refs": 20,
    "nt_refs": 3,
    "books_count": 11,
    "top_books": [
      "Amos",
      "1 Kings",
      "Isaiah",
      "Genesis",
      "Jeremiah",
      "2 Kings",
      "2 Corinthians",
      "Ezekiel",
      "2 Samuel",
      "Galatians"
    ]
  }
}