{
  "topic": "DRINK OFFERING",
  "slug": "drink_offering",
  "sources": [
    "NAV",
    "TOR"
  ],
  "see_also": [
    "OFFERING"
  ],
  "aspects": [
    {
      "label": "SeeOFFERING",
      "references": [],
      "source": "NAV"
    },
    {
      "label": "Antiquity of",
      "references": [
        "Genesis 35:14"
      ],
      "level": 1,
      "source": "TOR"
    },
    {
      "label": "Sacrifices accompanied by",
      "references": [
        "Exodus 29:40",
        "Leviticus 23:13"
      ],
      "level": 1,
      "source": "TOR"
    },
    {
      "label": "Quantity appointed to be used for each kind of sacrifice",
      "references": [
        "Numbers 15:3-10"
      ],
      "level": 1,
      "source": "TOR"
    },
    {
      "label": "For public sacrifices provided by the state",
      "references": [
        "Ezra 7:17",
        "Ezekiel 45:17"
      ],
      "level": 1,
      "source": "TOR"
    },
    {
      "label": "Not poured on the altar of incense",
      "references": [
        "Exodus 30:9"
      ],
      "level": 1,
      "source": "TOR"
    },
    {
      "label": "Omission of, caused by bad vintage",
      "references": [
        "Joel 1:9,13"
      ],
      "level": 1,
      "source": "TOR"
    },
    {
      "label": "Idolatrous Jews: Offered to the queen of heaven",
      "references": [
        "Jeremiah 7:18",
        "Jeremiah 44:17-19"
      ],
      "level": 1,
      "source": "TOR"
    },
    {
      "label": "Idolatrous Jews: Reproved for offering, to idols",
      "references": [
        "Isaiah 57:5,6",
        "Isaiah 65:11",
        "Jeremiah 19:13",
        "Ezekiel 20:28"
      ],
      "level": 1,
      "source": "TOR"
    },
    {
      "label": "Idolaters often used blood for",
      "references": [
        "Psalms 16:4"
      ],
      "level": 1,
      "source": "TOR"
    },
    {
      "label": "Vanity of offering, to idols",
      "references": [
        "Deuteronomy 32:37,38"
      ],
      "level": 1,
      "source": "TOR"
    },
    {
      "label": "Illustrative of the: Offering of Christ",
      "references": [
        "Isaiah 53:12"
      ],
      "level": 1,
      "source": "TOR"
    },
    {
      "label": "Illustrative of the: Pouring out of the Spirit",
      "references": [
        "Joel 2:28"
      ],
      "level": 1,
      "source": "TOR"
    },
    {
      "label": "Illustrative of the: Devotedness of ministers",
      "references": [
        "Philippians 2:17"
      ],
      "level": 1,
      "source": "TOR"
    }
  ],
  "biblical_references": [
    {
      "book": "Genesis",
      "chapter": 35,
      "verses": [
        14
      ],
      "verse_count": 1,
      "testament": "OT",
      "raw": "Genesis 35:14"
    },
    {
      "book": "Exodus",
      "chapter": 29,
      "verses": [
        40
      ],
      "verse_count": 1,
      "testament": "OT",
      "raw": "Exodus 29:40"
    },
    {
      "book": "Leviticus",
      "chapter": 23,
      "verses": [
        13
      ],
      "verse_count": 1,
      "testament": "OT",
      "raw": "Leviticus 23:13"
    },
    {
      "book": "Numbers",
      "chapter": 15,
      "verses": [
        3,
        4,
        5,
        6,
        7,
        8,
        9,
        10
      ],
      "verse_count": 8,
      "testament": "OT",
      "raw": "Numbers 15:3-10"
    },
    {
      "book": "Ezra",
      "chapter": 7,
      "verses": [
        17
      ],
      "verse_count": 1,
      "testament": "OT",
      "raw": "Ezra 7:17"
    },
    {
      "book": "Ezekiel",
      "chapter": 45,
      "verses": [
        17
      ],
      "verse_count": 1,
      "testament": "OT",
      "raw": "Ezekiel 45:17"
    },
    {
      "book": "Exodus",
      "chapter": 30,
      "verses": [
        9
      ],
      "verse_count": 1,
      "testament": "OT",
      "raw": "Exodus 30:9"
    },
    {
      "book": "Joel",
      "chapter": 1,
      "verses": [
        9,
        13
      ],
      "verse_count": 2,
      "testament": "OT",
      "raw": "Joel 1:9,13"
    },
    {
      "book": "Jeremiah",
      "chapter": 7,
      "verses": [
        18
      ],
      "verse_count": 1,
      "testament": "OT",
      "raw": "Jeremiah 7:18"
    },
    {
      "book": "Jeremiah",
      "chapter": 44,
      "verses": [
        17,
        18,
        19
      ],
      "verse_count": 3,
      "testament": "OT",
      "raw": "Jeremiah 44:17-19"
    },
    {
      "book": "Isaiah",
      "chapter": 57,
      "verses": [
        5,
        6
      ],
      "verse_count": 2,
      "testament": "OT",
      "raw": "Isaiah 57:5,6"
    },
    {
      "book": "Isaiah",
      "chapter": 65,
      "verses": [
        11
      ],
      "verse_count": 1,
      "testament": "OT",
      "raw": "Isaiah 65:11"
    },
    {
      "book": "Jeremiah",
      "chapter": 19,
      "verses": [
        13
      ],
      "verse_count": 1,
      "testament": "OT",
      "raw": "Jeremiah 19:13"
    },
    {
      "book": "Ezekiel",
      "chapter": 20,
      "verses": [
        28
      ],
      "verse_count": 1,
      "testament": "OT",
      "raw": "Ezekiel 20:28"
    },
    {
      "book": "Psalms",
      "chapter": 16,
      "verses": [
        4
      ],
      "verse_count": 1,
      "testament": "OT",
      "raw": "Psalms 16:4"
    },
    {
      "book": "Deuteronomy",
      "chapter": 32,
      "verses": [
        37,
        38
      ],
      "verse_count": 2,
      "testament": "OT",
      "raw": "Deuteronomy 32:37,38"
    },
    {
      "book": "Isaiah",
      "chapter": 53,
      "verses": [
        12
      ],
      "verse_count": 1,
      "testament": "OT",
      "raw": "Isaiah 53:12"
    },
    {
      "book": "Joel",
      "chapter": 2,
      "verses": [
        28
      ],
      "verse_count": 1,
      "testament": "OT",
      "raw": "Joel 2:28"
    },
    {
      "book": "Philippians",
      "chapter": 2,
      "verses": [
        17
      ],
      "verse_count": 1,
      "testament": "NT",
      "raw": "Philippians 2:17"
    }
  ],
  "books_mentioned": [
    "Deuteronomy",
    "Exodus",
    "Ezekiel",
    "Ezra",
    "Genesis",
    "Isaiah",
    "Jeremiah",
    "Joel",
    "Leviticus",
    "Numbers",
    "Philippians",
    "Psalms"
  ],
  "stats": {
    "total_aspects": 14,
    "total_refs": 19,
    "ot_refs": 18,
    "nt_refs": 1,
    "books_count": 12,
    "top_books": [
      "Jeremiah",
      "Isaiah",
      "Exodus",
      "Ezekiel",
      "Joel",
      "Genesis",
      "Leviticus",
      "Numbers",
      "Ezra",
      "Psalms"
    ]
  }
}