{
  "topic": "LEGS",
  "slug": "legs",
  "sources": [
    "NAV"
  ],
  "see_also": [],
  "aspects": [
    {
      "label": "Of the crucified, broken",
      "references": [
        "John 19:31,32"
      ],
      "source": "NAV"
    }
  ],
  "biblical_references": [
    {
      "book": "John",
      "chapter": 19,
      "verses": [
        31,
        32
      ],
      "verse_count": 2,
      "testament": "NT",
      "raw": "John 19:31,32"
    }
  ],
  "books_mentioned": [
    "John"
  ],
  "stats": {
    "total_aspects": 1,
    "total_refs": 1,
    "ot_refs": 0,
    "nt_refs": 1,
    "books_count": 1,
    "top_books": [
      "John"
    ]
  }
}